Metadata-Version: 2.1
Name: rapidstream-cocotbext-axi
Version: 0.1.25
Summary: AXI, AXI lite, and AXI stream modules for cocotb
Home-page: https://github.com/rapidstream-da/cocotbext-axi
Download-URL: https://github.com/rapidstream-da/cocotbext-axi/tarball/master
Author: Alex Forencich
Author-email: alex@alexforencich.com
License: MIT
Project-URL: Bug Tracker, https://github.com/rapidstream-da/cocotbext-axi/issues
Project-URL: Source Code, https://github.com/rapidstream-da/cocotbext-axi
Keywords: axi,cocotb
Platform: any
Classifier: Development Status :: 3 - Alpha
Classifier: Framework :: cocotb
Classifier: License :: OSI Approved :: MIT License
Classifier: Operating System :: OS Independent
Classifier: Programming Language :: Python :: 3
Classifier: Topic :: Scientific/Engineering :: Electronic Design Automation (EDA)
Requires-Python: >=3.6
License-File: LICENSE
Requires-Dist: rapidstream-cocotb>=1.6.0
Requires-Dist: rapidstream-cocotb-bus
Provides-Extra: test
Requires-Dist: pytest; extra == "test"
Requires-Dist: cocotb-test; extra == "test"
